README.rst
setup.py
src/PyFME.egg-info/PKG-INFO
src/PyFME.egg-info/SOURCES.txt
src/PyFME.egg-info/dependency_links.txt
src/PyFME.egg-info/not-zip-safe
src/PyFME.egg-info/requires.txt
src/PyFME.egg-info/top_level.txt
src/pyfme/__init__.py
src/pyfme/simulator.py
src/pyfme/aircrafts/__init__.py
src/pyfme/aircrafts/aircraft.py
src/pyfme/aircrafts/ball.py
src/pyfme/aircrafts/cessna_172.py
src/pyfme/aircrafts/cessna_310.py
src/pyfme/environment/__init__.py
src/pyfme/environment/atmosphere.py
src/pyfme/environment/environment.py
src/pyfme/environment/gravity.py
src/pyfme/environment/wind.py
src/pyfme/models/__init__.py
src/pyfme/models/constants.py
src/pyfme/models/euler_flat_earth.py
src/pyfme/models/systems.py
src/pyfme/utils/__init__.py
src/pyfme/utils/altimetry.py
src/pyfme/utils/anemometry.py
src/pyfme/utils/coordinates.py
src/pyfme/utils/input_generator.py
src/pyfme/utils/trimmer.py