Metadata-Version: 1.2
Name: PyFME
Version: 0.1.0
Summary: Python Flight Mechanics Engine
Home-page: http://pyfme.readthedocs.io/en/latest/
Author: AeroPython Team
Author-email: aeropython@groups.io
License: MIT
Download-URL: https://github.com/AeroPython/PyFME/
Keywords: aero,aerospace,engineering,flight mechanics,standard atmosphere,simulation
Platform: UNKNOWN
Classifier: Development Status :: 2 - Pre-Alpha
Classifier: Intended Audience :: Education
Classifier: Intended Audience :: Science/Research
Classifier: License :: OSI Approved :: MIT License
Classifier: Operating System :: OS Independent
Classifier: Programming Language :: Python
Classifier: Programming Language :: Python :: 3
Classifier: Programming Language :: Python :: 3.5
Classifier: Programming Language :: Python :: Implementation :: CPython
Classifier: Topic :: Scientific/Engineering
Classifier: Topic :: Scientific/Engineering :: Physics
Requires-Python: >=3.5
